code/__init__.py
code/load_data.py
code/main.py
code/main_spatial_val.py
code/main_temporal_val.py
code/preprocessing.py
code/spatial_embedding.py
code/utils.py
code/library/__init__.py
code/library/feature_extraction.py
code/library/featuring.py
code/library/signal_filtering.py
code/library/spfiltering.py
code/model/__init__.py
code/model/spatial_information.py
code/model/spatial_temporal_information.py
code/model/temporal_information.py
eeg_riemannian-1.10.0.dist-info/LICENSE
eeg_riemannian-1.10.0.dist-info/METADATA
eeg_riemannian-1.10.0.dist-info/WHEEL
eeg_riemannian-1.10.0.dist-info/top_level.txt
eeg_riemannian-1.10.0.dist-info/RECORD
