Metadata-Version: 2.1
Name: eeg-riemannian
Version: 1.10.0
Summary: Riemannian - Tensorflow
Home-page: https://github.com/guangyizhangbci/EEG_Riemannian
Author: Guangyi Zhang
Author-email: guangyi.zhang@utoronto.ca
License: MIT
Keywords: artificial intelligence,deep learning,riemannian manifold,eeg,emotion recognition
Classifier: Development Status :: 4 - Beta
Classifier: Intended Audience :: Developers
Classifier: Topic :: Scientific/Engineering :: Artificial Intelligence
Classifier: License :: OSI Approved :: MIT License
Classifier: Programming Language :: Python :: 3.6
License-File: LICENSE
Requires-Dist: numpy (>=1.19.5)
Requires-Dist: matplotlib (>=3.3.4)
Requires-Dist: tqdm (>=4.62.3)
Requires-Dist: rich (>=11.0.0)
Requires-Dist: pyriemann (>=0.2.7)
Requires-Dist: PyYAML (>=6.0)
Requires-Dist: scipy (>=1.5.4)
Requires-Dist: scikit-learn (>=0.24.2)
